teradatamlwidgets/LICENSE-3RD-PARTY.pdf
teradatamlwidgets/LICENSE.pdf
teradatamlwidgets/README.md
teradatamlwidgets/__init__.py
teradatamlwidgets/_version.py
teradatamlwidgets/base_ui.py
teradatamlwidgets/connection.py
teradatamlwidgets/connection_teradataml.py
teradatamlwidgets/custom_confirm_button.py
teradatamlwidgets/custom_destroy_button.py
teradatamlwidgets/exceptions.py
teradatamlwidgets/logo.png
teradatamlwidgets/my_tags_input.py
teradatamlwidgets/progress.gif
teradatamlwidgets/VAL/Adaptive Histogram VAL.json
teradatamlwidgets/VAL/Association VAL.json
teradatamlwidgets/VAL/Binning VAL.json
teradatamlwidgets/VAL/Binomial Test VAL.json
teradatamlwidgets/VAL/Chi Square Test VAL.json
teradatamlwidgets/VAL/Decision Tree Evaluate VAL.json
teradatamlwidgets/VAL/Decision Tree Predict VAL.json
teradatamlwidgets/VAL/Decision Tree VAL.json
teradatamlwidgets/VAL/Derive VAL.json
teradatamlwidgets/VAL/Explore VAL.json
teradatamlwidgets/VAL/Frequency VAL.json
teradatamlwidgets/VAL/Histogram VAL.json
teradatamlwidgets/VAL/K Means Predict VAL.json
teradatamlwidgets/VAL/K Means VAL.json
teradatamlwidgets/VAL/KS Test VAL.json
teradatamlwidgets/VAL/Label Encoder VAL.json
teradatamlwidgets/VAL/Linear Regression Evaluate VAL.json
teradatamlwidgets/VAL/Linear Regression Predict VAL.json
teradatamlwidgets/VAL/Linear Regression VAL.json
teradatamlwidgets/VAL/Logistic Regression Evaluate VAL.json
teradatamlwidgets/VAL/Logistic Regression Predict VAL.json
teradatamlwidgets/VAL/Logistic Regression VAL.json
teradatamlwidgets/VAL/Matrix VAL.json
teradatamlwidgets/VAL/Min Max Scalar VAL.json
teradatamlwidgets/VAL/One Hot Encoder VAL.json
teradatamlwidgets/VAL/Overlap VAL.json
teradatamlwidgets/VAL/Parametric Test VAL.json
teradatamlwidgets/VAL/Principal Component Analysis Evaluate VAL.json
teradatamlwidgets/VAL/Principal Component Analysis Predict VAL.json
teradatamlwidgets/VAL/Principal Component Analysis VAL.json
teradatamlwidgets/VAL/Rank Test VAL.json
teradatamlwidgets-20.0.0.6.dist-info/METADATA
teradatamlwidgets-20.0.0.6.dist-info/WHEEL
teradatamlwidgets-20.0.0.6.dist-info/top_level.txt
teradatamlwidgets-20.0.0.6.dist-info/RECORD
