Metadata-Version: 2.1
Name: teradatamlwidgets
Version: 20.0.0.6
Summary: Teradataml Widgets
Home-page: https://teradata.com
Author: Teradata Corporation
License: Teradata License Agreement
Platform: UNKNOWN
Classifier: Programming Language :: Python :: 3 :: Only
Classifier: Programming Language :: Python :: 3.9
Classifier: Operating System :: Microsoft :: Windows
Classifier: Operating System :: MacOS :: MacOS X
Classifier: Operating System :: POSIX :: Linux
Classifier: Topic :: Database :: Front-Ends
Classifier: License :: Other/Proprietary License
Requires-Python: >=3.8
Requires-Dist: teradataml (>=20.00.00.01)
Requires-Dist: ipywidgets (>=8.1.1)
